[
  {
    "key": "retrospaceadventure_card_effects",
    "value": [
      "apply_damage",
      "double_damage",
      "half_damage",
      "damage",
      "use_full_laser",
      "use_half_laser",
      "half_heal",
      "double_heal",
      "heal",
      "half_life_target",
      "half_life_self",
      "full_life_self",
      "full_life_target",
      "protect_self",
      "suffer_double_damage",
      "append_damage_to_laser_target",
      "half_laser_target",
      "damage_half_damage_self",
      "damage_half_damage_target",
      "switch_life",
      "no_effect"
    ],
    "description": "Effect of cards",
    "editable": false,
    "deletable": false,
    "module": "retrospaceadventure"
  },
  {
    "key": "retrospaceadventure_character_type",
    "value": ["hero", "enemy"],
    "description": "Character type",
    "editable": false,
    "deletable": false,
    "module": "retrospaceadventure"
  },
  {
    "key": "retrospaceadventure_character_default_life",
    "value": 1500,
    "description": "Effect of cards",
    "module": "retrospaceadventure",
    "editable": true,
    "deletable": false
  },
  {
    "key": "retrospaceadventure_character_default_laser",
    "value": 0,
    "description": "Characters default laser value",
    "module": "retrospaceadventure",
    "editable": true,
    "deletable": false
  },
  {
    "key": "retrospaceadventure_card_per_character",
    "value": 3,
    "description": "Characters default laser value",
    "module": "retrospaceadventure",
    "editable": true,
    "deletable": false
  },
  {
    "key": "retrospaceadventure_card_element",
    "value": [1, 2, 3],
    "description": "Elements",
    "module": "retrospaceadventure",
    "editable": false,
    "deletable": false
  },
  {
    "key": "retrospaceadventure_minigames",
    "value": ["touchgame", "breakout", "snake", "bossfight"],
    "description": "Mini games",
    "editable": false,
    "deletable": false,
    "module": "retrospaceadventure"
  },
  {
    "key": "retrospaceadventure_max_width_height_views",
    "value": [1200, 700],
    "description": "Max width and height for all views ( just not for home ), [width, height]",
    "editable": true,
    "deletable": false,
    "module": "retrospaceadventure"
  },
  {
    "key": "retrospaceadventure_max_width_height_minigames",
    "value": [600, 280],
    "description": "Max width and height for all mini games, [width, height]",
    "editable": true,
    "deletable": false,
    "module": "retrospaceadventure"
  }
]
