{"frames":[{"filename":"damage_sprite_3","frame":{"w":455,"h":1654,"x":0,"y":0},"anchor":{"x":0.5,"y":0.5}},{"filename":"heal_sprite_2","frame":{"w":457,"h":1656,"x":455,"y":0},"anchor":{"x":0.5,"y":0.5}},{"filename":"heal_sprite_1","frame":{"w":457,"h":1655,"x":912,"y":0},"anchor":{"x":0.5,"y":0.5}},{"filename":"idle_sprite_1","frame":{"w":455,"h":1654,"x":1369,"y":0},"anchor":{"x":0.5,"y":0.5}},{"filename":"idle_thumbnail_sprite_2","frame":{"w":55,"h":55,"x":1824,"y":0},"anchor":{"x":0.5,"y":0.5}},{"filename":"idle_thumbnail_sprite_1","frame":{"w":55,"h":55,"x":1879,"y":0},"anchor":{"x":0.5,"y":0.5}},{"filename":"idle_sprite_4","frame":{"w":455,"h":1654,"x":1934,"y":0},"anchor":{"x":0.5,"y":0.5}},{"filename":"idle_sprite_3","frame":{"w":455,"h":1654,"x":0,"y":1656},"anchor":{"x":0.5,"y":0.5}},{"filename":"damage_sprite_1","frame":{"w":455,"h":1654,"x":455,"y":1656},"anchor":{"x":0.5,"y":0.5}},{"filename":"idle_sprite_2","frame":{"w":455,"h":1654,"x":910,"y":1656},"anchor":{"x":0.5,"y":0.5}},{"filename":"damage_sprite_2","frame":{"w":455,"h":1654,"x":1365,"y":1656},"anchor":{"x":0.5,"y":0.5}}],"meta":{"description":"Atlas generado con Atlas Packer Gamma V2","web":"https://gammafp.github.io/atlas-packer-phaser/"}}