{
    "_title": "BD 16",
    "images": [
        {
            "src": "@a:Case17.jpg",
            "dialogsboxes": [
                {
                    "width": 23,
                    "height": 13,
                    "top": 10,
                    "left": 4,
                    "content": "@t:speech_bubble_23"
                },
                {
                    "width": 14,
                    "height": 10,
                    "top": 82,
                    "left": 31,
                    "content": "@t:speech_bubble_24",
                    "fontFamily": "Audiowide",
                    "fontStyle": "bold"
                },
                {
                    "width": 25,
                    "height": 13,
                    "top": 10,
                    "left": 71,
                    "content": "@t:speech_bubble_25"
                },
                {
                    "width": 17,
                    "height": 12,
                    "top": 82,
                    "left": 79,
                    "content": "@t:speech_bubble_26",
                    "fontFamily": "Audiowide",
                    "fontStyle": "bold"
                }
            ]
        }
    ],
    "_type": "retro-spacegame-adventure-comic-scene",
    "_module": "retrospaceadventure",
    "_actions": [
        {
            "_scene": "@s:49"
        }
    ],
    "_id": 33,
    "_font": "ihtacs",
    "_music": "@a:LaserGroove.mp3",
    "_canPrevScene": true,
    "_background": "@a:backgroundprimary.png"
}