{
    "_title": "Scene double comics inspecteur chef policier 1",
    "image": "@a:VIEUX-ET-POLICIER-cadre.jpg",
    "texts": [
        {
            "content": "@t:message_1749295874201",
            "character": "@go:2",
            "backgroundImage": "@a:VIEUX + POLICIER (2).jpg"
        },
        {
            "content": "@t:message_1749295874201",
            "character": "@go:1",
            "backgroundImage": "@a:VIEUX-ET-POLICIER-cadre.jpg"
        },
        {
            "content": "@t:message_1749295874201",
            "character": "@go:2",
            "backgroundImage": "@a:VIEUX + POLICIER (2).jpg"
        },
        {
            "content": "@t:message_1749295874201",
            "character": "@go:1",
            "backgroundImage": "@a:VIEUX-ET-POLICIER-cadre.jpg"
        }
    ],
    "_type": "SceneComicsDouble",
    "_module": "CaseoftheCenturyTheForbiddenCouple",
    "_actions": [
        {
            "_scene": "@s:5"
        }
    ],
    "_id": 4,
    "boxDialog": {
        "top": 77,
        "left": 11,
        "width": 81,
        "height": 16
    }
}